qpautomator/__init__.py
qpautomator-0.0.6.dist-info/LICENSE
qpautomator-0.0.6.dist-info/METADATA
qpautomator-0.0.6.dist-info/WHEEL
qpautomator-0.0.6.dist-info/top_level.txt
qpautomator-0.0.6.dist-info/RECORD
