Metadata-Version: 2.1
Name: qpautomator
Version: 0.0.6
Summary: automator on QPython3L
Home-page: https://github.com/qpautomator/xxxL
Author: mrsha
Author-email: mrsha1195@163.com
License: MIT
Download-URL: https://github.com/qpautomator/xxxL
Keywords: testing,android,qpautomator
Platform: any
Classifier: Development Status :: 3 - Alpha
Classifier: Environment :: Console
Classifier: Intended Audience :: Developers
Classifier: Operating System :: POSIX :: Linux
Classifier: Programming Language :: Python :: 2.7
Classifier: Programming Language :: Python :: 3.2
Classifier: Programming Language :: Python :: 3.3
Classifier: Programming Language :: Python :: 3.4
Classifier: Topic :: Software Development :: Libraries :: Python Modules
Classifier: Topic :: Software Development :: Testing
Requires-Dist: urllib3 (>=1.7.1)
Requires-Dist: requests (==2.22.0)
